datasette_publish_vercel/__init__.py
datasette_publish_vercel-0.14.2.dist-info/LICENSE
datasette_publish_vercel-0.14.2.dist-info/METADATA
datasette_publish_vercel-0.14.2.dist-info/WHEEL
datasette_publish_vercel-0.14.2.dist-info/entry_points.txt
datasette_publish_vercel-0.14.2.dist-info/top_level.txt
datasette_publish_vercel-0.14.2.dist-info/RECORD
