Metadata-Version: 2.1
Name: datasette-publish-vercel
Version: 0.14.2
Summary: Datasette plugin for publishing data using Vercel
Home-page: https://github.com/simonw/datasette-publish-vercel
Author: Simon Willison
License: Apache License, Version 2.0
Project-URL: Issues, https://github.com/simonw/datasette-publish-vercel/issues
Project-URL: CI, https://github.com/simonw/datasette-publish-vercel/actions
Project-URL: Changelog, https://github.com/simonw/datasette-publish-vercel/releases
License-File: LICENSE
Requires-Dist: datasette (>=0.59)
Provides-Extra: test
Requires-Dist: pytest ; extra == 'test'
